dash_labs/__init__.py
dash_labs/css.py
dash_labs/dashdown.py
dash_labs/util.py
dash_labs/version.py
dash_labs/plugins/__init__.py
dash_labs/plugins/pages.py
dash_labs/session/__init__.py
dash_labs/session/backends/__init__.py
dash_labs/session/backends/diskcache.py
dash_labs/session/backends/postgres.py
dash_labs/session/backends/redis.py
dash_labs-1.2.0.dist-info/LICENSE.txt
dash_labs-1.2.0.dist-info/METADATA
dash_labs-1.2.0.dist-info/WHEEL
dash_labs-1.2.0.dist-info/top_level.txt
dash_labs-1.2.0.dist-info/RECORD
