Metadata-Version: 2.1
Name: dash-labs
Version: 1.2.0
Summary: Experimental enhancements for potential inclusion in Dash
Home-page: https://github.com/plotly/dash-labs
Author: Chris Parmer
Author-email: chris@plot.ly
Maintainer: Chris Parmer
Maintainer-email: chris@plot.ly
License: MIT
Project-URL: Github, https://github.com/plotly/dash-labs
Platform: UNKNOWN
Classifier: Development Status :: 4 - Beta
Classifier: Programming Language :: Python :: 3.6
Classifier: Programming Language :: Python :: 3.7
Classifier: Programming Language :: Python :: 3.8
Classifier: Programming Language :: Python :: 3.9
Classifier: Topic :: Scientific/Engineering :: Visualization
Classifier: Framework :: Dash
Requires-Python: >=3.6.*
Provides-Extra: diskcache
Provides-Extra: redis
Provides-Extra: postgres
